azure_cli_diff_tool/__init__.py
azure_cli_diff_tool/_const.py
azure_cli_diff_tool/meta_change.py
azure_cli_diff_tool/meta_change_detect.py
azure_cli_diff_tool/utils.py
azure_cli_diff_tool/data/blob_config.ini
azure_cli_diff_tool/data/meta_change_whitelist.txt
tests/__init__.py
tests/test_break_change.py
azure_cli_diff_tool-0.1.1.dist-info/METADATA
azure_cli_diff_tool-0.1.1.dist-info/WHEEL
azure_cli_diff_tool-0.1.1.dist-info/top_level.txt
azure_cli_diff_tool-0.1.1.dist-info/RECORD
