Metadata-Version: 2.4
Name: azure-cli-diff-tool
Version: 0.1.1
Summary: A tool for cli metadata management
Author: Microsoft Corporation
Author-email: azpycli@microsoft.com
License: MIT
Requires-Dist: deepdiff~=8.6.1
Requires-Dist: requests~=2.32.3
Dynamic: author
Dynamic: author-email
Dynamic: description
Dynamic: license
Dynamic: requires-dist
Dynamic: summary
